petharbor/__init__.py
petharbor/advance.py
petharbor/data/pet_names_hashed.txt
petharbor/utils/__init__.py
petharbor/utils/dataset.py
petharbor/utils/logging_setup.py
petharbor/utils/processor_model.py
petharbor-0.2.4.dist-info/METADATA
petharbor-0.2.4.dist-info/WHEEL
petharbor-0.2.4.dist-info/licenses/LICENSE
petharbor-0.2.4.dist-info/RECORD
