Metadata-Version: 2.4
Name: petharbor
Version: 0.2.4
Summary: PetHarbor is a Python package designed for anonymizing datasets using either a pre-trained model or a hash-based approach.
License: MIT
License-File: LICENSE
Author: Sean Farrell
Author-email: sean.farrell2@durham.ac.uk
Requires-Python: >=3.9
Classifier: License :: OSI Approved :: MIT License
Classifier: Programming Language :: Python :: 3
Classifier: Programming Language :: Python :: 3.9
Classifier: Programming Language :: Python :: 3.10
Classifier: Programming Language :: Python :: 3.11
Classifier: Programming Language :: Python :: 3.12
Classifier: Programming Language :: Python :: 3.13
Classifier: Programming Language :: Python :: 3.14
Requires-Dist: accelerate (==1.6.0)
Requires-Dist: colorlog (>=6.9.0)
Requires-Dist: datasets (>=3.5.0)
Requires-Dist: importlib-metadata
Requires-Dist: jaraco-collections
Requires-Dist: pandas (>=2.0)
Requires-Dist: protobuf (>=5.26.1)
Requires-Dist: pysocks (>=1.7.1)
Requires-Dist: sentencepiece (>=0.1.99)
Requires-Dist: spacy (>=3.5.4)
Requires-Dist: tomli (>=2.0.1)
Requires-Dist: torch (>=2.2.0)
Requires-Dist: transformers (>=4.51.0)
